adafruit_circuitpython_hx711-1.0.8.dist-info/licenses/LICENSE
adafruit_hx711/analog_in.py
adafruit_hx711/hx711.py
adafruit_circuitpython_hx711-1.0.8.dist-info/METADATA
adafruit_circuitpython_hx711-1.0.8.dist-info/WHEEL
adafruit_circuitpython_hx711-1.0.8.dist-info/top_level.txt
adafruit_circuitpython_hx711-1.0.8.dist-info/RECORD
