Metadata-Version: 2.4
Name: adafruit-circuitpython-hx711
Version: 1.0.8
Summary: CircuitPython driver for the HX711 24-bit ADC for Load Cells / Strain Gauges
Author-email: Adafruit Industries <circuitpython@adafruit.com>
License: MIT
Project-URL: Homepage, https://github.com/adafruit/Adafruit_CircuitPython_HX711
Keywords: adafruit,blinka,circuitpython,micropython,hx711,ADC,,strain,gauge
Classifier: Intended Audience :: Developers
Classifier: Topic :: Software Development :: Libraries
Classifier: Topic :: Software Development :: Embedded Systems
Classifier: Topic :: System :: Hardware
Classifier: License :: OSI Approved :: MIT License
Classifier: Programming Language :: Python :: 3
License-File: LICENSE
Requires-Dist: Adafruit-Blinka
Provides-Extra: optional
Dynamic: license-file
